{
 "page": 66,
 "dpi": 300,
 "mixed": "VA\nGLEE ‏بج‎ oat.\n‏ب‎ a 7\n. ‏لبطيخة كبيرة و حلوة - هذهاللبطيخة كبيرة 4 حلوة‎ |\nছবি দেখে উত্তর 718١ ‏التمرين الأول‎\n<>\n\nماهذه ؟ ‎KEN‏\n\n- الأول\n\n‎e ০ -‏ 7 $ * . “ 2\nهل هي جميلة ؛ هل هي ر[خيصة ‎a>) 1S‏ هي | م ‎ale‏ §\n‎রণ‏ ري ‎ঢাক নন নই‏\nاساعة الطاولة هذه ام ‎এ 125৮০‏ ؟ ساعة من هذه ؟\n‎SS পু ° | 1‏\n\n‏ء و . £ ‎Se weed -. ৫‏ ل\nأ تفاحة تلك أمركانة ؟ ا\n\n‎- £ ~ ‏ع و‎ রি € . . « ০ তা ন্‌\n। ‏صغيرة هي | م كبيرة ؟ أ حلوة هي | م حامضة‎ I$ ‏كيف التفاحة‎\nপেলে\n\n‎= Le) র্‌ - ‏عمد هد‎\n\n‎Saws ‏نب‎ °\n\n‎CE 2 4. - - 7‏\nكيف العقد ؟ هل العقد جميل ؟ تون\n\n‎নে aA € নে\n\n‏هل هو رخيص ؟ ‎١‏ رخيص هو ام ‎Le‏ ل 1 ‎sie‏ من هنا ؛اعقد\nكيف السبورة ؟ | نظيفة هي أم وَسخّة ؟ . ‎ড়‏\n‎এ. 1 - 3 - - |‏ 7\nالخ ‎z , - রা‏\nرخيص ‎সম্তা‏ يوار ‎লম্বা, দীর্ঘ ০১৯৮৮ বালা, চুড়ি‏ قصير ‎খাটো‏",
 "arabic": "عدي\nم ار بج 7\n\nا لتمرين ا لأول ‎7198١‏ 7 اكفية! 1\nكيفٌ السائّة ؟ او .\n\n.0 ِ راون ءءء . 12\nء. م م 7 ‎٠‏ ع * و م ص\nاساعة الطاولة هذه ام ساعة النّد ؟ ساعة مَنْ هذه ؟\n\n‎١‏ | ّ اليج\nما تلك ؟ لل\nأ تفاحة تلك أم ركانة ؟ ل\nكيف التفاحّة ؟ أ صغيرة هي أم كبيرة ؟ أ خلوة هي أم حامضة؟\n. .8 ار . ا حر 0 َ\nاعقد هذا ام سوار ؟ 7ج حا\n7 : , ِو كدر للب ديت\n\n‏كيف أ لعقد ؟ هل العقد جميل ؟ “09م\n\n‏. ع م ع : 8 م . ع\nهل هو رخيص ؟أرخيص هوام غالٍ ؟ عقد من هذا ؛اعقد\nكيف السبورّة ؟ ٍ نظيفة هي ام وسخة ؟ 7 لا\n7.2 ِ رع 7 ٍِ ٍِ\nرخيص | 3 يسار 05> طويل 838 قصير 451",
 "mixedFixed": "بج oat.\n. لبطيخة كبيرة و حلوة - هذهاللبطيخة كبيرة حلوة\nছবি দেখে উত্তর 718١ التمرين الأول\nماهذه ؟\n- الأول\n০ - . “\nهل هي جميلة ؛ هل هي ر[خيصة a>) هي م §\nরণ ري ঢাক নন নই\nاساعة الطاولة هذه ام এ 125৮০ ؟ ساعة من هذه ؟\nপু °\nء و . £ -. ৫ ل\nأ تفاحة تلك أمركانة ؟ ا\n- £ ع و রি € . . « ০ তা ন্‌\n। صغيرة هي م كبيرة ؟ أ حلوة هي م حامضة كيف التفاحة\nপেলে\nLe) র্‌ - عمد هد\nنب °\nكيف العقد ؟ هل العقد جميل ؟ تون\nনে € নে\nهل هو رخيص ؟ ١ رخيص هو ام ل من هنا ؛اعقد\nكيف السبورة ؟ نظيفة هي أم وَسخّة ؟ . ড়\nএ. - - -\nالخ , - রা\nرخيص সম্তা يوار লম্বা, দীর্ঘ ০১৯৮৮ বালা, চুড়ি قصير খাটো",
 "arabicFixed": "عدي\nم ار بج\nا لتمرين ا لأول 7198١ اكفية!\nكيفٌ السائّة ؟ او .\n.0 ِ راون ءءء .\nء. م م ٠ ع و م ص\nاساعة الطاولة هذه ام ساعة النّد ؟ ساعة مَنْ هذه ؟\n١ ّ اليج\nما تلك ؟ لل\nأ تفاحة تلك أم ركانة ؟ ل\nكيف التفاحّة ؟ أ صغيرة هي أم كبيرة ؟ أ خلوة هي أم حامضة؟\n. .8 ار . ا حر َ\nاعقد هذا ام سوار ؟ 7ج حا\n: , ِو كدر للب ديت\nكيف أ لعقد ؟ هل العقد جميل ؟ “09م\n. ع م ع : م . ع\nهل هو رخيص ؟أرخيص هوام غالٍ ؟ عقد من هذا ؛اعقد\nكيف السبورّة ؟ ٍ نظيفة هي ام وسخة ؟ لا\n7.2 ِ رع ٍِ ٍِ\nرخيص يسار طويل قصير"
}
