{
  "id": 36,
  "title": "সম্বোধন (নিদা)",
  "sub": "يا وَلَدُ! أَيُّهَا الْوَلَدُ! أَيَّتُهَا الْبِنْتُ!",
  "icon": "📣",
  "tip": "কাউকে ডাকতে <b>يا</b>: <span class='ar'>يا بِلالُ!</span><br><b>ال</b>-ওয়ালা শব্দে পুংলিঙ্গে <b>أَيُّها</b>, স্ত্রীলিঙ্গে <b>أَيَّتُها</b>।<br>ছেলেদের নামে তানভীন হয় (<span class='ar'>خالِدٌ</span>), মেয়েদের নামে হয় না (<span class='ar'>فاطِمَةُ</span>)।",
  "learn": [
    "<b>মূল নিয়ম (নিদা = সম্বোধন):</b> কাউকে ডাকার জন্য আরবিতে তিনটি রূপ:<br>",
    "<b>১) <span class='ar'>يا</span></b> — নাম বা সাধারণ শব্দের আগে: <span class='ar'>يا بِلالُ!</span> হে বিলাল! · <span class='ar'>يا وَلَدُ!</span> হে ছেলে!<br>",
    "👉 খেয়াল করো: <span class='ar'>يا</span>-এর পরের শব্দ <b>পেশ</b> নেয়, তানভীন নয় (<span class='ar'>يا وَلَدُ</span>, <span class='ar'>يا وَلَدٌ</span> নয়)।<br>",
    "<b>২) <span class='ar'>أَيُّها</span></b> — <b>ال</b>-ওয়ালা পুংলিঙ্গ শব্দের আগে: <span class='ar'>أَيُّهَا الْمُسْلِمُ!</span> হে মুসলিম!<br>",
    "<b>৩) <span class='ar'>أَيَّتُها</span></b> — <b>ال</b>-ওয়ালা স্ত্রীলিঙ্গ শব্দের আগে: <span class='ar'>أَيَّتُهَا الْبِنْتُ!</span> হে মেয়ে!<br>",
    "<b>📌 নামের তানভীনের নিয়ম:</b> ছেলেদের নামে তানভীন হয় — <span class='ar'>خالِدٌ، راشِدٌ، مَحْمُودٌ</span>; কিন্তু মেয়েদের নামে তানভীন <b>হয় না</b> — <span class='ar'>فاطِمَةُ، عائِشَةُ، زَيْنَبُ</span>।"
  ],
  "vocab": [
    {
      "a": "يا",
      "b": "হে! (ডাকার হরফ)"
    },
    {
      "a": "أَيُّها",
      "b": "হে (পুংলিঙ্গ)"
    },
    {
      "a": "أَيَّتُها",
      "b": "হে (স্ত্রীলিঙ্গ)"
    },
    {
      "a": "يا وَلَدُ",
      "b": "হে ছেলে!",
      "img": "👦"
    },
    {
      "a": "يا بِنْتُ",
      "b": "হে মেয়ে!",
      "img": "👧"
    },
    {
      "a": "أَيُّهَا الْمُسْلِمُ",
      "b": "হে মুসলিম!"
    },
    {
      "a": "أَيُّهَا الْإِنْسانُ",
      "b": "হে মানুষ!"
    },
    {
      "a": "أَيَّتُهَا الْبِنْتُ",
      "b": "হে মেয়ে!"
    },
    {
      "a": "خالِدٌ",
      "b": "খালিদ (ছেলের নাম)"
    },
    {
      "a": "فاطِمَةُ",
      "b": "ফাতেমা (মেয়ের নাম)"
    },
    {
      "a": "نِداءٌ",
      "b": "সম্বোধন"
    }
  ],
  "sents": [
    {
      "a": "يا بِلالُ! اِجْلِسْ هُنا",
      "b": "হে বিলাল! এখানে বসো"
    },
    {
      "a": "يا فاطِمَةُ! اُكْتُبِي دَرْسَكِ",
      "b": "হে ফাতেমা! তোমার পাঠ লেখো"
    },
    {
      "a": "أَيُّهَا الْوَلَدُ! لا تَكْذِبْ",
      "b": "হে ছেলে! মিথ্যা বলো না"
    },
    {
      "a": "أَيَّتُهَا الْبِنْتُ! اُكْتُبِي بِقَلَمِكِ",
      "b": "হে মেয়ে! তোমার কলম দিয়ে লেখো"
    },
    {
      "a": "أَيُّهَا الْإِنْسانُ! اِرْجِعْ إِلى رَبِّكَ",
      "b": "হে মানুষ! তোমার রবের দিকে ফিরে এসো"
    },
    {
      "a": "أَيُّهَا الْمُسْلِمُ! اُطْلُبِ الْعِلْمَ",
      "b": "হে মুসলিম! জ্ঞান অন্বেষণ কর"
    },
    {
      "a": "يا أُمِّي! أَنْتِ اِمْرَأَةٌ طَيِّبَةٌ",
      "b": "হে আমার আম্মা! আপনি একজন ভালো মানুষ",
      "img": "👩"
    },
    {
      "a": "هٰذا خالِدٌ وَ تِلْكَ فاطِمَةُ",
      "b": "ইনি খালিদ এবং উনি ফাতেমা"
    }
  ],
  "qa": [
    {
      "q": "كَيْفَ تُنادِي وَلَدًا اسْمُهُ بِلالٌ؟",
      "o": [
        "يا بِلالُ!",
        "أَيَّتُها بِلالُ!",
        "يا الْبِلالُ!"
      ],
      "c": 0
    },
    {
      "q": "أَيُّ حَرْفٍ لِلْبِنْتِ مَعَ ال؟",
      "o": [
        "أَيَّتُها",
        "أَيُّها",
        "يا"
      ],
      "c": 0
    },
    {
      "q": "أَيُّ اسْمٍ فِيهِ تَنْوِينٌ؟",
      "o": [
        "خالِدٌ",
        "فاطِمَةُ",
        "زَيْنَبُ"
      ],
      "c": 0
    }
  ],
  "fill": [
    {
      "q": "يا ... ! اِجْلِسْ",
      "o": [
        "وَلَدُ",
        "الْوَلَدُ"
      ],
      "c": 0
    },
    {
      "q": "... الْمُسْلِمُ! اُطْلُبِ الْعِلْمَ",
      "o": [
        "أَيُّهَا",
        "أَيَّتُهَا"
      ],
      "c": 0
    },
    {
      "q": "... الْبِنْتُ! اُكْتُبِي",
      "o": [
        "أَيَّتُهَا",
        "أَيُّهَا"
      ],
      "c": 0
    }
  ]
}
